ChangeLog
LICENSE
MANIFEST.in
README
setup.py
bin/ewa
bin/ewabatch
bin/ewasplice
conf/ewa.conf.sample
conf/lighttpd.conf.sample
conf/rules.conf.sample
doc/Makefile
doc/ewamanual.html
doc/ewamanual.rst
doc/style.css
doc/api/Makefile
doc/api/html/class-tree.html
doc/api/html/epydoc.css
doc/api/html/ewa-module.html
doc/api/html/ewa-pysrc.html
doc/api/html/ewa._ruletab-module.html
doc/api/html/ewa._ruletab-pysrc.html
doc/api/html/ewa.audio-module.html
doc/api/html/ewa.audio-pysrc.html
doc/api/html/ewa.audio.AudioProviderException-class.html
doc/api/html/ewa.audio.BaseAudioProvider-class.html
doc/api/html/ewa.audio.FSAudioProvider-class.html
doc/api/html/ewa.audio.FileNotFound-class.html
doc/api/html/ewa.audio.StreamAudioProvider-class.html
doc/api/html/ewa.buffutil-module.html
doc/api/html/ewa.buffutil-pysrc.html
doc/api/html/ewa.clisupport-module.html
doc/api/html/ewa.clisupport-pysrc.html
doc/api/html/ewa.clisupport.DeleteFinder-class.html
doc/api/html/ewa.clisupport.RecursiveChangedMp3FileIterator-class.html
doc/api/html/ewa.clisupport.RecursiveMp3FileIterator-class.html
doc/api/html/ewa.config-module.html
doc/api/html/ewa.config-pysrc.html
doc/api/html/ewa.config._config-class.html
doc/api/html/ewa.frameinfo-module.html
doc/api/html/ewa.lighttpd_hack_middleware-module.html
doc/api/html/ewa.lighttpd_hack_middleware-pysrc.html
doc/api/html/ewa.lighttpd_hack_middleware.LighttpdHackMiddleware-class.html
doc/api/html/ewa.logutil-module.html
doc/api/html/ewa.logutil-pysrc.html
doc/api/html/ewa.mp3-module.html
doc/api/html/ewa.mp3-pysrc.html
doc/api/html/ewa.ply-module.html
doc/api/html/ewa.ply-pysrc.html
doc/api/html/ewa.ply.cpp-module.html
doc/api/html/ewa.ply.cpp-pysrc.html
doc/api/html/ewa.ply.cpp.Macro-class.html
doc/api/html/ewa.ply.cpp.Preprocessor-class.html
doc/api/html/ewa.ply.ctokens-module.html
doc/api/html/ewa.ply.ctokens-pysrc.html
doc/api/html/ewa.ply.lex-module.html
doc/api/html/ewa.ply.lex-pysrc.html
doc/api/html/ewa.ply.lex.LexError-class.html
src/ewa.egg-info/PKG-INFO
src/ewa.egg-info/SOURCES.txt
src/ewa.egg-info/dependency_links.txt
src/ewa.egg-info/requires.txt
src/ewa.egg-info/top_level.txt
src/ewa.egg-info/zip-safe
