Metadata-Version: 1.0
Name: ewa
Version: 0.62.8
Summary: an mp3 splicing system
Home-page: http://eastwestaudio.wnyc.org/
Author: Jacob Smullyan
Author-email: jsmullyan@gmail.com
License: GPL
Keywords: mp3,audio
Platform: OS Independent
